sseed/__init__.py
sseed/__main__.py
sseed/bip39.py
sseed/cli.py
sseed/exceptions.py
sseed/languages.py
sseed/logging_config.py
sseed/slip39_operations.py
sseed/bip85/__init__.py
sseed/bip85/applications.py
sseed/bip85/cache.py
sseed/bip85/core.py
sseed/bip85/exceptions.py
sseed/bip85/optimized_applications.py
sseed/bip85/paths.py
sseed/bip85/security.py
sseed/cli/__init__.py
sseed/cli/base.py
sseed/cli/error_handling.py
sseed/cli/examples.py
sseed/cli/main.py
sseed/cli/parser.py
sseed/cli/commands/__init__.py
sseed/cli/commands/bip85.py
sseed/cli/commands/derive_addresses.py
sseed/cli/commands/gen.py
sseed/cli/commands/restore.py
sseed/cli/commands/seed.py
sseed/cli/commands/shard.py
sseed/cli/commands/validate.py
sseed/cli/commands/version.py
sseed/entropy/__init__.py
sseed/entropy/core.py
sseed/entropy/custom.py
sseed/file_operations/__init__.py
sseed/file_operations/formatters.py
sseed/file_operations/readers.py
sseed/file_operations/validators.py
sseed/file_operations/writers.py
sseed/hd_wallet/__init__.py
sseed/hd_wallet/addresses.py
sseed/hd_wallet/coins.py
sseed/hd_wallet/core.py
sseed/hd_wallet/derivation.py
sseed/hd_wallet/exceptions.py
sseed/hd_wallet/extended_keys.py
sseed/hd_wallet/validation.py
sseed/validation/__init__.py
sseed/validation/analysis.py
sseed/validation/backup_verification.py
sseed/validation/batch.py
sseed/validation/cross_tool.py
sseed/validation/crypto.py
sseed/validation/formatters.py
sseed/validation/input.py
sseed/validation/structure.py
sseed-1.12.1.dist-info/licenses/LICENSE
sseed-1.12.1.dist-info/METADATA
sseed-1.12.1.dist-info/WHEEL
sseed-1.12.1.dist-info/entry_points.txt
sseed-1.12.1.dist-info/top_level.txt
sseed-1.12.1.dist-info/RECORD
