Metadata-Version: 2.4
Name: sseed
Version: 1.12.1
Summary: Offline BIP39/SLIP39 CLI Tool for secure cryptocurrency seed management
Author-email: sseed <shroomshroom@gmail.com>
License-Expression: MIT
Keywords: bip39,slip39,cryptocurrency,mnemonic,seed,cli,offline
Classifier: Development Status :: 5 - Production/Stable
Classifier: Intended Audience :: Developers
Classifier: Operating System :: OS Independent
Classifier: Programming Language :: Python :: 3
Classifier: Programming Language :: Python :: 3.10
Classifier: Programming Language :: Python :: 3.11
Classifier: Programming Language :: Python :: 3.12
Classifier: Topic :: Security :: Cryptography
Classifier: Topic :: System :: Systems Administration
Requires-Python: >=3.10
License-File: LICENSE
Requires-Dist: bip-utils>=2.9.3
Requires-Dist: shamir-mnemonic>=0.3.0
Provides-Extra: dev
Requires-Dist: pytest>=8.3.4; extra == "dev"
Requires-Dist: pytest-asyncio>=0.23.5; extra == "dev"
Requires-Dist: pytest-cov>=4.1.0; extra == "dev"
Requires-Dist: pytest-xdist>=3.6.1; extra == "dev"
Requires-Dist: pytest-html>=4.1.1; extra == "dev"
Requires-Dist: pytest-benchmark>=4.0.0; extra == "dev"
Requires-Dist: hypothesis>=6.112.0; extra == "dev"
Requires-Dist: coverage[toml]>=7.3.0; extra == "dev"
Requires-Dist: pylint>=3.0.0; extra == "dev"
Requires-Dist: mypy>=1.16.1; extra == "dev"
Requires-Dist: flake8>=7.0.0; extra == "dev"
Requires-Dist: black>=25.1.0; extra == "dev"
Requires-Dist: isort>=5.13.0; extra == "dev"
Requires-Dist: ruff>=0.12.0; extra == "dev"
Requires-Dist: bandit>=1.8.5; extra == "dev"
Requires-Dist: safety>=3.0.0; extra == "dev"
Requires-Dist: pip-audit>=2.6.0; extra == "dev"
Requires-Dist: build>=1.0.0; extra == "dev"
Requires-Dist: twine>=4.0.0; extra == "dev"
Requires-Dist: wheel>=0.42.0; extra == "dev"
Requires-Dist: setuptools>=69.0.0; extra == "dev"
Requires-Dist: psutil>=5.9.0; extra == "dev"
Requires-Dist: memory-profiler>=0.61.0; extra == "dev"
Requires-Dist: shamir-mnemonic[cli]>=0.3.0; extra == "dev"
Dynamic: license-file
